odoo/addons/ssi_customer_rent/README.rst
odoo/addons/ssi_customer_rent/__init__.py
odoo/addons/ssi_customer_rent/__manifest__.py
odoo/addons/ssi_customer_rent/menu.xml
odoo/addons/ssi_customer_rent/data/approval_template_data.xml
odoo/addons/ssi_customer_rent/data/ir_sequence_data.xml
odoo/addons/ssi_customer_rent/data/policy_template_data.xml
odoo/addons/ssi_customer_rent/data/sequence_template_data.xml
odoo/addons/ssi_customer_rent/models/__init__.py
odoo/addons/ssi_customer_rent/models/customer_rent_order.py
odoo/addons/ssi_customer_rent/models/customer_rent_order_payment_schedule.py
odoo/addons/ssi_customer_rent/models/customer_rent_type.py
odoo/addons/ssi_customer_rent/security/ir.model.access.csv
odoo/addons/ssi_customer_rent/security/ir_module_category_data.xml
odoo/addons/ssi_customer_rent/security/ir_rule_data.xml
odoo/addons/ssi_customer_rent/security/res_group_data.xml
odoo/addons/ssi_customer_rent/static/description/icon.png
odoo/addons/ssi_customer_rent/views/customer_rent_order_views.xml
odoo/addons/ssi_customer_rent/views/customer_rent_type_views.xml
odoo14_addon_ssi_customer_rent-14.0.2.0.0.dist-info/METADATA
odoo14_addon_ssi_customer_rent-14.0.2.0.0.dist-info/WHEEL
odoo14_addon_ssi_customer_rent-14.0.2.0.0.dist-info/top_level.txt
odoo14_addon_ssi_customer_rent-14.0.2.0.0.dist-info/RECORD
